README.html
README.txt
setup.cfg
setup.py
docs/HISTORY.txt
docs/INSTALL.txt
docs/LICENSE.GPL
docs/LICENSE.txt
getpaid/__init__.py
getpaid.realex.egg-info/PKG-INFO
getpaid.realex.egg-info/SOURCES.txt
getpaid.realex.egg-info/dependency_links.txt
getpaid.realex.egg-info/entry_points.txt
getpaid.realex.egg-info/namespace_packages.txt
getpaid.realex.egg-info/not-zip-safe
getpaid.realex.egg-info/paster_plugins.txt
getpaid.realex.egg-info/requires.txt
getpaid.realex.egg-info/top_level.txt
getpaid/realex/__init__.py
getpaid/realex/aborthook.py
getpaid/realex/configure.zcml
getpaid/realex/realex.py
getpaid/realex/realex.txt
getpaid/realex/realexoptions.py
getpaid/realex/realexprocessor.py
getpaid/realex/tests.py