Metadata-Version: 1.0
Name: getpaid.realex
Version: 1.0
Summary: Realex plugin for Plone GetPaid (www.realexpayments.com)
Home-page: http://svn.plone.org/svn/collective/
Author: Kevin Gill
Author-email: kevin@movieextras.ie
License: GPL
Keywords: getpaid,ecommerce,payment
Platform: UNKNOWN
Classifier: Framework :: Plone
Classifier: Programming Language :: Python
